pyev3/__init__.py
pyev3/brick.py
pyev3/comm.py
pyev3/devices.py
pyev3/io.py
pyev3/utils.py
pyev3-0.0.5.dist-info/LICENSE.txt
pyev3-0.0.5.dist-info/METADATA
pyev3-0.0.5.dist-info/WHEEL
pyev3-0.0.5.dist-info/top_level.txt
pyev3-0.0.5.dist-info/RECORD
