Metadata-Version: 2.1
Name: pyev3
Version: 0.0.5
Summary: Direct Commands for LEGO EV3
Home-page: https://github.com/EduardoNigro/pyev3
Author: Eduardo Nigro
Author-email: eduardo.b.nigro@gmail.com
License: UNKNOWN
Project-URL: Bug Tracker, https://github.com/EduardoNigro/pyev3/issues
Platform: UNKNOWN
Classifier: Programming Language :: Python :: 3
Classifier: License :: OSI Approved :: MIT License
Classifier: Operating System :: Microsoft :: Windows :: Windows 10
Requires-Python: >=3.6
License-File: LICENSE.txt
Requires-Dist: hidapi
Requires-Dist: numpy
Requires-Dist: plotly
